starlette_jsonrpc/__init__.py
starlette_jsonrpc/constants.py
starlette_jsonrpc/dispatcher.py
starlette_jsonrpc/endpoint.py
starlette_jsonrpc/exceptions.py
starlette_jsonrpc/schemas.py
starlette_jsonrpc/server.py
tests/__init__.py
tests/test_dispatcher.py
tests/test_requests.py
tests/test_validating.py
tests/tests_validating/__init__.py
tests/tests_validating/test_batch.py
starlette_jsonrpc-0.2.0.dist-info/LICENSE
starlette_jsonrpc-0.2.0.dist-info/METADATA
starlette_jsonrpc-0.2.0.dist-info/WHEEL
starlette_jsonrpc-0.2.0.dist-info/top_level.txt
starlette_jsonrpc-0.2.0.dist-info/RECORD
