Metadata-Version: 2.1
Name: starlette-jsonrpc
Version: 0.2.0
Summary: JSON-RPC implementation for Starlette framework
Home-page: https://github.com/kdebowski/starlette-jsonrpc
Author: Kamil Dębowski
Author-email: poczta@kdebowski.pl
License: UNKNOWN
Platform: UNKNOWN
Classifier: Development Status :: 3 - Alpha
Classifier: Programming Language :: Python :: 3
Classifier: License :: OSI Approved :: MIT License
Classifier: Operating System :: OS Independent
Classifier: Intended Audience :: Developers
Requires-Dist: requests (==2.21.0)
Requires-Dist: starlette (==0.11.4)
Requires-Dist: typesystem (==0.2.0)
